coresptbr/__init__.py
coresptbr/cores.py
coresptbr-0.1.0.dist-info/LICENSE
coresptbr-0.1.0.dist-info/METADATA
coresptbr-0.1.0.dist-info/WHEEL
coresptbr-0.1.0.dist-info/top_level.txt
coresptbr-0.1.0.dist-info/RECORD
