Metadata-Version: 2.1
Name: coresptbr
Version: 0.1.0
Summary: Um pacote de cores em pt-br simples.
Home-page: https://github.com/nugovit/cores_ptbr
Author: Rafael C. de Paula (nugovit)
Author-email: rafael.personalizado@gmail.com
License: UNKNOWN
Project-URL: Bug Tracker, https://github.com/nugovit/cores_ptbr
Platform: UNKNOWN
Classifier: Programming Language :: Python :: 3
Classifier: License :: OSI Approved :: MIT License
Classifier: Operating System :: OS Independent
Requires-Python: >=3.6
License-File: LICENSE
